cmvc/__init__.py
cmvc/scripts/__init__.py
cmvc/scripts/dec.py
cmvc/scripts/enc.py
cmvc/scripts/layer.py
cmvc/scripts/model.py
cmvc-0.0.2.dist-info/LICENSE
cmvc-0.0.2.dist-info/WHEEL
cmvc-0.0.2.dist-info/METADATA
cmvc-0.0.2.dist-info/RECORD
